MANIFEST.in
README.rst
setup.py
grvlms_socialoauth.egg-info/PKG-INFO
grvlms_socialoauth.egg-info/SOURCES.txt
grvlms_socialoauth.egg-info/dependency_links.txt
grvlms_socialoauth.egg-info/entry_points.txt
grvlms_socialoauth.egg-info/requires.txt
grvlms_socialoauth.egg-info/top_level.txt
grvlmssocialoauth/__about__.py
grvlmssocialoauth/__init__.py
grvlmssocialoauth/plugin.py
grvlmssocialoauth/patches/.gitignore
grvlmssocialoauth/patches/common-env-features
grvlmssocialoauth/patches/lms-env
grvlmssocialoauth/patches/openedx-auth
grvlmssocialoauth/patches/openedx-dockerfile-pre-assets
grvlmssocialoauth/patches/openedx-lms-common-settings
grvlmssocialoauth/templates/.DS_Store
grvlmssocialoauth/templates/socialoauth/apps/.gitignore
grvlmssocialoauth/templates/socialoauth/build/.gitignore
grvlmssocialoauth/templates/socialoauth/hooks/.gitignore
grvlmssocialoauth/templates/socialoauth/hooks/lms/init